Workbook

Sheet README
A1: Week 1 - AI-Ready Networks Market Intelligence
A2: Owner | B2: Akhil Hari Nair | Tata Communications (US-focused) internship
A3: Prepared | B3: 2026-06-10 | Draft dataset for the Week 1 dashboard
A4: Scope | B4: US / Americas market for AI-ready enterprise networking. All competitors treated as US players.
A5: !! CONFIDENTIALITY | B5: Treat this as internal Tata material. Build and SAVE LOCALLY in Tableau Desktop Public Edition (.twbx). Do NOT click 'Save to Tableau Public' - anything published there is public on the web and downloadable by anyone. Share with your supervisor via exported PDF/PNG images and the local .twbx (openable in free Tableau Reader).
A6: TABS
A7: Findings_Log | B7: Raw research log - 35 real, sourced, paraphrased findings to start. KEEP ADDING ROWS.
A8: Topic_Source_Heatmap | B8: Live COUNTIFS cross-tab (tidy) for the Page-2 heatmap.
A9: Keyword_Frequency | B9: Live keyword counts (substring match) for 'Top 10 keywords'.
A10: Vendor_Mentions | B10: Live vendor mention counts + positioning notes for Page 3.
A11: Analyst_Predictions | B11: Curated analyst predictions for the exec summary.
A12: Top10_Trends | B12: Curated top-10 market trends with evidence + Tata relevance.
A13: CONTROLLED VOCABULARY
A14: Source_Type | B14: Analyst Report | Market Research | Industry News | Vendor (Primary) | LinkedIn/Social (add)
A15: Topic | B15: Market Sizing & Spend; AI Back-End / GPU Fabric; Ethernet vs NVLink (Scale-up); High-Speed Optics; Network Observability; AIOps / Autonomous Networks; NaaS / Cloud Connectivity; Private / Sovereign AI; Network Security (Zero-Trust); Power & Sustainability; Adoption Barriers & Skills; Competitive / M&A; Vendor Product Launch
A16: Finding_Type | B16: Trend | Statistic | Prediction | Challenge | Priority | Announcement | Messaging
A17: Use the SAME spellings | B17: so the live counts and Tableau filters stay clean.
A18: LINKEDIN ROWS | B18: Not pre-filled (LinkedIn blocks automated collection and it's against ToS). Add a handful of rows manually from a sample of US CIO / infra-leader posts, tagging Source_Type = LinkedIn/Social.
A19: ON THE NUMBERS | B19: Findings_Log facts are real and sourced (see Source_URL). The heatmap/keyword/vendor counts are LIVE off your log, so early numbers are small and grow as you research. The email's '85/74/65' were illustrative of a large corpus.

Sheet Findings_Log
A1: Finding_ID | B1: Date_Captured | C1: Source_Type | D1: Source_Name | E1: Pub_Date | F1: Region | G1: Topic | H1: Finding_Type | I1: Finding_Summary | J1: Key_Statistic | K1: Keywords (; sep) | L1: Vendors_Mentioned (; sep) | M1: Relevance_to_Tata | N1: Confidence | O1: Source_URL
A2: F001 | B2: 2026-06-10 | C2: Analyst Report | D2: Gartner | E2: Apr 2026 | F2: Global | G2: Market Sizing & Spend | H2: Statistic | I2: Worldwide IT spending is forecast to reach roughly $6.31T in 2026 (+13.5% YoY), with data center spending growing ~55.8% to over $788B, driven mainly by AI infrastructure buildouts. | J2: $6.31T IT spend; DC +55.8% | K2: AI infrastructure;data center spend;IT spending | L2: — | M2: High | N2: High | O2: https://www.ciodive.com/news/global-it-spend-exceed-6T-2026/818356/
A3: F002 | B3: 2026-06-10 | C3: Analyst Report | D3: Gartner | E3: Sep 2025 / Feb 2026 | F3: Global | G3: Market Sizing & Spend | H3: Prediction | I3: Global AI spending is projected to top $2T in 2026 (up from ~$1.5T in 2025); AI infrastructure alone is expected to add ~$401B, led by hyperscaler data center investment. | J3: $2T AI spend; +$401B infra | K3: AI spend;hyperscaler;AI infrastructure | L3: — | M3: High | N3: High | O3: https://www.computerweekly.com/news/366638605/Gartner-AI-and-datacentre-spending-ramps
A4: F003 | B4: 2026-06-10 | C4: Analyst Report | D4: IDC | E4: Oct 2025 | F4: Global | G4: Market Sizing & Spend | H4: Prediction | I4: IDC forecasts the worldwide AI infrastructure market to reach ~$758B in spending by 2029, driven by hyperscalers, cloud providers, and research/education. | J4: $758B AI infra by 2029 | K4: AI infrastructure;hyperscaler;cloud | L4: — | M4: High | N4: High | O4: https://my.idc.com/getdoc.jsp?containerId=prUS53894425
A5: F004 | B5: 2026-06-10 | C5: Analyst Report | D5: IDC (via Network World) | E5: Q3 2025 / Feb 2026 | F5: Global | G5: High-Speed Optics | H5: Statistic | I5: The data center segment of the Ethernet switch market grew ~62% YoY in Q3 2025 as high-bandwidth, low-latency AI networking accelerated; 800GbE switch revenue jumped ~92% sequentially. | J5: DC Ethernet +62% YoY; 800G +92% QoQ | K5: 800G;Ethernet;data center switch;low latency | L5: — | M5: High | N5: High | O5: https://www.networkworld.com/article/4126582/8-hot-networking-trends-for-2026.html
A6: F005 | B6: 2026-06-10 | C6: Market Research | D6: ResearchAndMarkets | E6: May 2026 | F6: Global | G6: Market Sizing & Spend | H6: Statistic | I6: The AI data center networking market is projected to grow from ~$10.3B (2025) to ~$12.8B (2026), a 24.2% CAGR, reaching ~$30B by 2030 on demand for low-latency fabrics and optical interconnects. | J6: $10.3B->$12.8B (24.2% CAGR); $30B by 2030 | K6: AI networking;data center;optical interconnect | L6: — | M6: High | N6: Medium | O6: https://www.globenewswire.com/news-release/2026/05/20/3298728/0/en/ai-data-center-networking-global-market-analysis-report-2026.html
A7: F006 | B7: 2026-06-10 | C7: Analyst Report | D7: McKinsey (cited by Cisco) | E7: 2025 | F7: Global | G7: Market Sizing & Spend | H7: Statistic | I7: Cumulative global data center IT equipment spend (servers, accelerators, networking, optics, storage) could reach ~$4.7T between 2025 and 2030. | J7: $4.7T DC equipment 2025-2030 | K7: data center;accelerators;networking;optics | L7: Cisco | M7: High | N7: Medium | O7: https://www.networkworld.com/article/4113462/ciscos-2026-agenda-prioritizes-ai-ready-infrastructure-connectivity.html
A8: F007 | B8: 2026-06-10 | C8: Analyst Report | D8: Dell'Oro Group | E8: Jan 2026 | F8: Global | G8: AI Back-End / GPU Fabric | H8: Trend | I8: Ethernet data center switch revenue hit an all-time high in 2025, nearly doubling 2022 levels, propelled by rapid adoption in AI back-end (GPU cluster) networks. | J8: Ethernet DC switch revenue ~2x vs 2022 | K8: AI back-end;GPU fabric;Ethernet;scale-out | L8: Arista;NVIDIA | M8: High | N8: High | O8: https://www.delloro.com/2026-predictions-data-center-switch-frontend-ai-backed-networks/
A9: F008 | B9: 2026-06-10 | C9: Analyst Report | D9: Dell'Oro Group | E9: Jan 2026 | F9: Global | G9: Ethernet vs NVLink (Scale-up) | H9: Prediction | I9: 'Scale-up' GPU interconnect (within-rack) is emerging as the next battleground for Ethernet against NVIDIA NVLink and UALink; 2026 will bring a wave of vendor announcements. | J9: Scale-up = largest new TAM opportunity | K9: scale-up;NVLink;UALink;Ethernet;GPU | L9: NVIDIA | M9: High | N9: High | O9: https://www.networkworld.com/article/4113462/ciscos-2026-agenda-prioritizes-ai-ready-infrastructure-connectivity.html
A10: F009 | B10: 2026-06-10 | C10: Analyst Report | D10: Forrester | E10: Feb 2026 | F10: Global | G10: Private / Sovereign AI | H10: Prediction | I10: At least 15% of enterprises will shift toward private AI deployments built on private clouds in 2026, reacting to rising AI cost, data lock-in, and operational risk. | J10: >=15% enterprises -> private AI in 2026 | K10: private AI;private cloud;data sovereignty | L10: — | M10: High | N10: High | O10: https://www.networkworld.com/article/4126582/8-hot-networking-trends-for-2026.html
A11: F010 | B11: 2026-06-10 | C11: Analyst Report | D11: ONUG (via Network World) | E11: Feb 2026 | F11: US | G11: AIOps / Autonomous Networks | H11: Prediction | I11: In 2026 Tier-1 and Tier-2 infrastructure operations will move to 'no human in the loop,' with agentic AI autonomously handling incident response and remediation. | J11: Tier 1/2 ops -> no human in the loop | K11: agentic AI;autonomous networks;AIOps;incident response | L11: — | M11: Medium | N11: Medium | O11: https://www.networkworld.com/article/4126582/8-hot-networking-trends-for-2026.html
A12: F011 | B12: 2026-06-10 | C12: Analyst Report | D12: IDC (via Network World) | E12: Feb 2026 | F12: Global | G12: AIOps / Autonomous Networks | H12: Statistic | I12: An IDC survey of 500+ practitioners shows a sharp rise in the share of network-management tasks automated by AI, expected to gain momentum over the next two years. | J12: 500+ respondents; rising AI automation | K12: network automation;AIOps;agentic | L12: — | M12: Medium | N12: High | O12: https://www.networkworld.com/article/4126582/8-hot-networking-trends-for-2026.html
... A36: F035 | B36: 2026-06-10 | C36: Analyst Report | D36: Gartner (via Itential) | E36: Dec 2025 | F36: Global | G36: AIOps / Autonomous Networks | H36: Trend | I36: Network operators are aligning to agentic operations using API-first orchestration that translates natural-language intent into governed workflows across network, cloud, and security. | J36: API-first agentic orchestration | K36: orchestration;agentic;API-first;intent | L36: Lumen | M36: Medium | N36: Medium | O36: https://www.itential.com/resource/analyst-report/gartner-predicts-2026-ai-agents-will-reshape-infrastructure-operations/

Sheet Topic_Source_Heatmap
A1: Topic | B1: Source_Type | C1: Finding_Count
A2: Market Sizing & Spend | B2: Analyst Report | C2: =COUNTIFS(Findings_Log!$G$2:$G$36,$A2,Findings_Log!$C$2:$C$36,$B2) -> 5
A3: Market Sizing & Spend | B3: Market Research | C3: =COUNTIFS(Findings_Log!$G$2:$G$36,$A3,Findings_Log!$C$2:$C$36,$B3) -> 1
A4: Market Sizing & Spend | B4: Industry News | C4: =COUNTIFS(Findings_Log!$G$2:$G$36,$A4,Findings_Log!$C$2:$C$36,$B4) -> 0
A5: Market Sizing & Spend | B5: Vendor (Primary) | C5: =COUNTIFS(Findings_Log!$G$2:$G$36,$A5,Findings_Log!$C$2:$C$36,$B5) -> 1
A6: AI Back-End / GPU Fabric | B6: Analyst Report | C6: =COUNTIFS(Findings_Log!$G$2:$G$36,$A6,Findings_Log!$C$2:$C$36,$B6) -> 2
A7: AI Back-End / GPU Fabric | B7: Market Research | C7: =COUNTIFS(Findings_Log!$G$2:$G$36,$A7,Findings_Log!$C$2:$C$36,$B7) -> 0
A8: AI Back-End / GPU Fabric | B8: Industry News | C8: =COUNTIFS(Findings_Log!$G$2:$G$36,$A8,Findings_Log!$C$2:$C$36,$B8) -> 0
A9: AI Back-End / GPU Fabric | B9: Vendor (Primary) | C9: =COUNTIFS(Findings_Log!$G$2:$G$36,$A9,Findings_Log!$C$2:$C$36,$B9) -> 0
A10: Ethernet vs NVLink (Scale-up) | B10: Analyst Report | C10: =COUNTIFS(Findings_Log!$G$2:$G$36,$A10,Findings_Log!$C$2:$C$36,$B10) -> 1
A11: Ethernet vs NVLink (Scale-up) | B11: Market Research | C11: =COUNTIFS(Findings_Log!$G$2:$G$36,$A11,Findings_Log!$C$2:$C$36,$B11) -> 0
A12: Ethernet vs NVLink (Scale-up) | B12: Industry News | C12: =COUNTIFS(Findings_Log!$G$2:$G$36,$A12,Findings_Log!$C$2:$C$36,$B12) -> 1
A13: Ethernet vs NVLink (Scale-up) | B13: Vendor (Primary) | C13: =COUNTIFS(Findings_Log!$G$2:$G$36,$A13,Findings_Log!$C$2:$C$36,$B13) -> 0
... A53: Vendor Product Launch | B53: Vendor (Primary) | C53: =COUNTIFS(Findings_Log!$G$2:$G$36,$A53,Findings_Log!$C$2:$C$36,$B53) -> 2

Sheet Keyword_Frequency
A1: Keyword | B1: Category | C1: Mention_Count (live) | D1: Trend_Direction
A2: AI infrastructure | B2: Market | C2: =COUNTIF(Findings_Log!$K$2:$K$36,"*"&A2&"*")+COUNTIF(Findings_Log!$I$2:$I$36,"*"&A2&"*") -> 9 | D2: Rising
A3: network observability | B3: Operations | C3: =COUNTIF(Findings_Log!$K$2:$K$36,"*"&A3&"*")+COUNTIF(Findings_Log!$I$2:$I$36,"*"&A3&"*") -> 1 | D3: Rising
A4: GPU | B4: Fabric | C4: =COUNTIF(Findings_Log!$K$2:$K$36,"*"&A4&"*")+COUNTIF(Findings_Log!$I$2:$I$36,"*"&A4&"*") -> 12 | D4: Rising
A5: Ethernet | B5: Fabric | C5: =COUNTIF(Findings_Log!$K$2:$K$36,"*"&A5&"*")+COUNTIF(Findings_Log!$I$2:$I$36,"*"&A5&"*") -> 8 | D5: Rising
A6: scale-up | B6: Fabric | C6: =COUNTIF(Findings_Log!$K$2:$K$36,"*"&A6&"*")+COUNTIF(Findings_Log!$I$2:$I$36,"*"&A6&"*") -> 5 | D6: Emerging
A7: AIOps | B7: Operations | C7: =COUNTIF(Findings_Log!$K$2:$K$36,"*"&A7&"*")+COUNTIF(Findings_Log!$I$2:$I$36,"*"&A7&"*") -> 6 | D7: Rising
A8: agentic | B8: Operations | C8: =COUNTIF(Findings_Log!$K$2:$K$36,"*"&A8&"*")+COUNTIF(Findings_Log!$I$2:$I$36,"*"&A8&"*") -> 8 | D8: Emerging
A9: 800G | B9: Optics | C9: =COUNTIF(Findings_Log!$K$2:$K$36,"*"&A9&"*")+COUNTIF(Findings_Log!$I$2:$I$36,"*"&A9&"*") -> 2 | D9: Rising
A10: NaaS | B10: Connectivity | C10: =COUNTIF(Findings_Log!$K$2:$K$36,"*"&A10&"*")+COUNTIF(Findings_Log!$I$2:$I$36,"*"&A10&"*") -> 3 | D10: Rising
A11: PCF | B11: Connectivity | C11: =COUNTIF(Findings_Log!$K$2:$K$36,"*"&A11&"*")+COUNTIF(Findings_Log!$I$2:$I$36,"*"&A11&"*") -> 4 | D11: Emerging
A12: private AI | B12: Strategy | C12: =COUNTIF(Findings_Log!$K$2:$K$36,"*"&A12&"*")+COUNTIF(Findings_Log!$I$2:$I$36,"*"&A12&"*") -> 2 | D12: Emerging
A13: SONiC | B13: Fabric | C13: =COUNTIF(Findings_Log!$K$2:$K$36,"*"&A13&"*")+COUNTIF(Findings_Log!$I$2:$I$36,"*"&A13&"*") -> 4 | D13: Emerging
... A21: Mist | B21: Vendor | C21: =COUNTIF(Findings_Log!$K$2:$K$36,"*"&A21&"*")+COUNTIF(Findings_Log!$I$2:$I$36,"*"&A21&"*") -> 4 | D21: Steady

Sheet Vendor_Mentions
A1: Vendor | B1: Category | C1: Mention_Count (live) | D1: AI-Networking Positioning (1-line) | E1: Watch in Week 2?
A2: Cisco | B2: Networking vendor | C2: =COUNTIF(Findings_Log!$L$2:$L$36,"*"&A2&"*") -> 8 | D2: Network as 'AI innovation platform'; Silicon One G300, Nexus One, AI Job Observability, AgenticOps. | E2: Yes
A3: HPE/Juniper | B3: Networking vendor | C3: =COUNTIF(Findings_Log!$L$2:$L$36,"*"&A3&"*") -> 3 | D3: 'AI-native' networking after $14B Juniper deal; Mist AIOps + GreenLake; 'AI for / Networking for AI'. | E3: Yes
A4: Juniper | B4: Networking vendor | C4: =COUNTIF(Findings_Log!$L$2:$L$36,"*"&A4&"*") -> 5 | D4: Now part of HPE; Mist AIOps remains a Gartner-recognized AI-native asset. | E4: Yes
A5: Arista | B5: Networking vendor | C5: =COUNTIF(Findings_Log!$L$2:$L$36,"*"&A5&"*") -> 1 | D5: Leader in Ethernet AI back-end (scale-out) switching; strong cloud/AI fabric share. | E5: Yes
A6: NVIDIA | B6: Silicon / fabric | C6: =COUNTIF(Findings_Log!$L$2:$L$36,"*"&A6&"*") -> 6 | D6: Spectrum-X Ethernet + NVLink/InfiniBand; sets the GPU-fabric reference for the whole market. | E6: Yes
A7: Lumen | B7: Telco / NSP | C7: =COUNTIF(Findings_Log!$L$2:$L$36,"*"&A7&"*") -> 6 | D7: 'Tech-first' AI infra partner; Private Connectivity Fabric, NaaS, hyperscaler fiber deals. | E7: Yes (primary)
A8: AT&T | B8: Telco / NSP | C8: =COUNTIF(Findings_Log!$L$2:$L$36,"*"&A8&"*") -> 0 | D8: US enterprise connectivity, edge, fiber; AI-era network modernization - capture in Week 2. | E8: Yes (primary)
A9: Verizon | B9: Telco / NSP | C9: =COUNTIF(Findings_Log!$L$2:$L$36,"*"&A9&"*") -> 0 | D9: US enterprise, private 5G, edge compute; AI connectivity angle - capture in Week 2. | E9: Yes (primary)
A10: NTT DATA | B10: Telco / NSP | C10: =COUNTIF(Findings_Log!$L$2:$L$36,"*"&A10&"*") -> 0 | D10: Global data centers + network; major AI data-center builder - capture in Week 2. | E10: Yes (primary)
A11: Orange Business | B11: Telco / NSP | C11: =COUNTIF(Findings_Log!$L$2:$L$36,"*"&A11&"*") -> 0 | D11: Europe-centric NSP; managed networks / NaaS - capture in Week 2. | E11: Yes (primary)
A12: Equinix | B12: Data center / interconnect | C12: =COUNTIF(Findings_Log!$L$2:$L$36,"*"&A12&"*") -> 0 | D12: Fabric interconnect + xScale data centers; neutral AI interconnection hub. | E12: Yes
A13: Tata Communications | B13: Telco / NSP (baseline) | C13: =COUNTIF(Findings_Log!$L$2:$L$36,"*"&A13&"*") -> 3 | D13: Global digital fabric, IZO multi-cloud, Vayu (India only); differentiator = global reach. | E13: Baseline
... A15: Google | B15: Hyperscaler | C15: =COUNTIF(Findings_Log!$L$2:$L$36,"*"&A15&"*") -> 2 | D15: Google Cloud NaaS partnership w/ Lumen; AI infra demand driver. | E15: Context

Sheet Analyst_Predictions
A1: Source | B1: Prediction | C1: Timeframe | D1: Key Metric | E1: Relevance to Tata (US)
A2: Gartner | B2: Global AI spending tops $2T; AI infrastructure adds ~$401B. | C2: 2026 | D2: $2T / +$401B | E2: Validates the size of the AI-network opportunity Tata is targeting.
A3: Gartner | B3: Data center spending grows ~55.8% to >$788B; power doubles in ~4 yrs. | C3: 2026-2030 | D3: +55.8% DC; 2x power | E3: Power/site constraints favor providers with global footprint & efficient DCs.
A4: IDC | B4: Worldwide AI infrastructure spend reaches ~$758B. | C4: by 2029 | D4: $758B | E4: Long runway; supports multi-year account targeting.
A5: Forrester | B5: >=15% of enterprises shift to private AI on private clouds. | C5: 2026 | D5: 15% | E5: Direct fit for managed/sovereign connectivity & private fabric offers.
A6: Dell'Oro | B6: Ethernet expands into scale-up; SONiC adoption accelerates. | C6: 2026 | D6: scale-up TAM | E6: Open Ethernet/SONiC lowers lock-in - relevant to NSP positioning.
A7: ONUG | B7: Tier-1/2 network ops go 'no human in the loop' (agentic). | C7: 2026 | D7: autonomy | E7: AIOps becomes table-stakes messaging for any network provider.
A8: Gartner | B8: AI agents take over complex I&O tasks; governance becomes critical. | C8: 2026-2028 | D8: agentic I&O | E8: Governance + ISO 42001 is a credible Tata differentiator.
A9: IDC | B9: Operational readiness, security & skills are top AI-network barriers. | C9: 2025-2027 | D9: top 3 barriers | E9: Managed services narrative addresses the skills-gap barrier directly.

Sheet Top10_Trends
A1: Rank | B1: Market Trend | C1: One-line Description | D1: Evidence (source example) | E1: Tata (US) Relevance
A2: 1 | B2: AI is rewiring the data-center network | C2: GPU clusters force high-bandwidth, low-latency back-end fabrics. | D2: IDC: DC Ethernet +62% YoY (Q3'25) | E2: Core demand signal for AI-ready network conversations.
A3: 2 | B3: Ethernet beats proprietary fabric | C3: Ethernet (incl. SONiC) expands from scale-out into scale-up vs NVLink/UALink. | D3: Dell'Oro 2026 predictions | E3: Open standards reduce lock-in; align messaging accordingly.
A4: 3 | B4: 800G / 1.6T optics go mainstream | C4: Highest-speed ports drive switch revenue; co-packaged optics emerge. | D4: IDC: 800G +92% QoQ | E4: High-capacity transport is the product conversation.
A5: 4 | B5: Network observability is mandatory | C5: Job-aware, network-to-GPU visibility correlates telemetry with workloads. | D5: Cisco AI Job Observability | E5: Observability is a key theme to claim in the matrix.
A6: 5 | B6: Agentic / self-driving operations | C6: Tier-1/2 ops move toward 'no human in the loop'; AIOps everywhere. | D6: ONUG; Gartner Predicts 2026 | E6: AIOps + governance is differentiating messaging.
A7: 6 | B7: Network capacity is the new scarce resource | C7: Fiber/routes ranked with power, space, cooling as AI constraints. | D7: Lumen (Fierce) | E7: Reframes connectivity as strategic, not commodity.
A8: 7 | B8: Private & sovereign AI rising | C8: Enterprises move to private AI to cut cost, lock-in, and risk. | D8: Forrester: >=15% in 2026 | E8: Strong fit for managed/sovereign-grade connectivity.
A9: 8 | B9: NaaS & multi-cloud connectivity | C9: Programmable, on-demand cloud-to-cloud fabric for AI workloads. | D9: Lumen PCF / Multi-Cloud Gateway | E9: Maps to IZO / digital-fabric positioning.
A10: 9 | B10: Vendor landscape consolidating | C10: HPE+Juniper reshapes competition vs Cisco, Arista, NVIDIA. | D10: HPE closes $14B Juniper deal | E10: Competitive set has shifted - update Week 2 matrix.
A11: 10 | B11: Power & sustainability constrain buildout | C11: DC power projected to ~2x in four years under AI demand. | D11: Gartner | E11: Efficient DCs + global siting are advantages.
